loadtext/__about__.py
loadtext/__init__.py
loadtext/loadtext.py
loadtext-0.0.3.dist-info/METADATA
loadtext-0.0.3.dist-info/WHEEL
loadtext-0.0.3.dist-info/licenses/LICENSE.txt
loadtext-0.0.3.dist-info/RECORD
