Metadata-Version: 2.1
Name: loadtext
Version: 0.0.3
Summary: Load a text file as a string or a list of paragraphs (when splitlines is set to True) with blank lines removed
Project-URL: Documentation, https://github.com/ffreemt/loadtext#readme
Project-URL: Issues, https://github.com/ffreemt/loadtext/issues
Project-URL: Source, https://github.com/ffreemt/loadtext
Author: ffreemt
License-Expression: MIT
License-File: LICENSE.txt
Classifier: Development Status :: 4 - Beta
Classifier: Programming Language :: Python
Classifier: Programming Language :: Python :: 3.8
Classifier: Programming Language :: Python :: 3.9
Classifier: Programming Language :: Python :: 3.10
Classifier: Programming Language :: Python :: 3.11
Classifier: Programming Language :: Python :: 3.12
Classifier: Programming Language :: Python :: Implementation :: CPython
Classifier: Programming Language :: Python :: Implementation :: PyPy
Requires-Python: >=3.8
Requires-Dist: charset-normalizer
Requires-Dist: loguru
